ursa/__init__.py
ursa/agents/__init__.py
ursa/agents/acquisition_agents.py
ursa/agents/arxiv_agent.py
ursa/agents/base.py
ursa/agents/chat_agent.py
ursa/agents/code_review_agent.py
ursa/agents/execution_agent.py
ursa/agents/hypothesizer_agent.py
ursa/agents/lammps_agent.py
ursa/agents/mp_agent.py
ursa/agents/optimization_agent.py
ursa/agents/planning_agent.py
ursa/agents/rag_agent.py
ursa/agents/recall_agent.py
ursa/agents/websearch_agent.py
ursa/cli/__init__.py
ursa/cli/hitl.py
ursa/cli/hitl_api.py
ursa/observability/metrics_charts.py
ursa/observability/metrics_io.py
ursa/observability/metrics_session.py
ursa/observability/pricing.json
ursa/observability/pricing.py
ursa/observability/timing.py
ursa/prompt_library/__init__.py
ursa/prompt_library/code_review_prompts.py
ursa/prompt_library/execution_prompts.py
ursa/prompt_library/hypothesizer_prompts.py
ursa/prompt_library/literature_prompts.py
ursa/prompt_library/optimization_prompts.py
ursa/prompt_library/planning_prompts.py
ursa/prompt_library/websearch_prompts.py
ursa/tools/__init__.py
ursa/tools/feasibility_checker.py
ursa/tools/feasibility_tools.py
ursa/tools/fm_base_tool.py
ursa/tools/read_file_tool.py
ursa/tools/run_command_tool.py
ursa/tools/search_tools.py
ursa/tools/write_code_tool.py
ursa/util/__init__.py
ursa/util/diff_renderer.py
ursa/util/helperFunctions.py
ursa/util/logo_generator.py
ursa/util/memory_logger.py
ursa/util/optimization_schema.py
ursa/util/parse.py
ursa/util/plan_renderer.py
ursa_ai-0.13.3.dist-info/licenses/LICENSE
ursa_ai-0.13.3.dist-info/METADATA
ursa_ai-0.13.3.dist-info/WHEEL
ursa_ai-0.13.3.dist-info/entry_points.txt
ursa_ai-0.13.3.dist-info/top_level.txt
ursa_ai-0.13.3.dist-info/RECORD
