Metadata-Version: 2.4
Name: ursa-ai
Version: 0.13.3
Summary: Agents for science at LANL
Author-email: Mike Grosskopf <mikegros@lanl.gov>, Nathan Debardeleben <ndebard@lanl.gov>, Rahul Somasundaram <rsomasundaram@lanl.gov>, Isaac Michaud <imichaud@lanl.gov>, Avanish Mishra <avanish@lanl.gov>, Arthur Lui <alui@lanl.gov>, Russell Bent <rbent@lanl.gov>, Earl Lawrence <earl@lanl.gov>
License-Expression: BSD-3-Clause
Project-URL: Homepage, https://github.com/lanl/ursa
Project-URL: Documentation, https://github.com/lanl/ursa/tree/main/docs
Project-URL: Repository, https://github.com/lanl/ursa
Project-URL: Issues, https://github.com/lanl/ursa/issues
Classifier: Operating System :: OS Independent
Classifier: Programming Language :: Python :: 3.10
Classifier: Programming Language :: Python :: 3.11
Classifier: Programming Language :: Python :: 3.12
Classifier: Programming Language :: Python :: 3.13
Classifier: Programming Language :: Python :: 3.14
Requires-Python: >=3.10
License-File: LICENSE
Requires-Dist: arxiv<3.0,>=2.2.0
Requires-Dist: beautifulsoup4<5.0,>=4.13.4
Requires-Dist: randomname<0.3,>=0.2.1
Requires-Dist: pandas<3.0,>=2.3.1
Requires-Dist: pillow<12.0,>=11.3.0
Requires-Dist: pymupdf<2.0,>=1.26.0
Requires-Dist: pypdf<6.0,>=5.9.0
Requires-Dist: rich<14.0,>=13.9.4
Requires-Dist: mp-api<0.45.13,>=0.45.8
Requires-Dist: ddgs>=9.5.5
Requires-Dist: typer>=0.16.1
Requires-Dist: trafilatura<1.7,>=1.6.1
Requires-Dist: selectolax<0.5,>=0.4.0
Requires-Dist: langchain>=1.0.3
Requires-Dist: langchain-chroma>=1.0.0
Requires-Dist: langchain-community>=0.4.1
Requires-Dist: langchain-openai>=1.0.1
Requires-Dist: langgraph-checkpoint-sqlite>=3.0.0
Requires-Dist: langchain-text-splitters>=1.0.0
Requires-Dist: langchain-ollama>=1.0.0
Requires-Dist: langchain-mcp-adapters<0.2,>=0.1.12
Requires-Dist: pydantic<3.0,>=2.12.0
Requires-Dist: mcp<2.0,>=1.20.0
Provides-Extra: fm
Requires-Dist: torch>=2.9.0; extra == "fm"
Dynamic: license-file
